episode_manager/__init__.py
episode_manager/config.py
episode_manager/context.py
episode_manager/db.py
episode_manager/epm.py
episode_manager/progress.py
episode_manager/styles.py
episode_manager/tmdb.py
episode_manager/utils.py
episode_manager-0.14.post1.dist-info/entry_points.txt
episode_manager-0.14.post1.dist-info/LICENSE
episode_manager-0.14.post1.dist-info/WHEEL
episode_manager-0.14.post1.dist-info/METADATA
episode_manager-0.14.post1.dist-info/RECORD
