Metadata-Version: 2.1
Name: episode-manager
Version: 0.14.post1
Summary: Keep track of your episode viewing and schedule.
License: MIT
Author: André Jonsson
Author-email: episode-manager@0x1.se
Requires-Python: >=3.9,<4.0
Classifier: Development Status :: 4 - Beta
Classifier: Environment :: Console
Classifier: Intended Audience :: End Users/Desktop
Classifier: License :: OSI Approved :: MIT License
Classifier: Operating System :: POSIX :: Linux
Classifier: Programming Language :: Python :: 3
Classifier: Programming Language :: Python :: 3.10
Classifier: Programming Language :: Python :: 3.9
Classifier: Topic :: Games/Entertainment
Classifier: Topic :: Utilities
Requires-Dist: requests (>=2.28.1,<3.0.0)
